nfcl/__init__.py
nfcl/core.py
nfcl-0.1.1.dist-info/METADATA
nfcl-0.1.1.dist-info/WHEEL
nfcl-0.1.1.dist-info/top_level.txt
nfcl-0.1.1.dist-info/RECORD
