Metadata-Version: 2.4
Name: NFCL
Version: 0.1.1
Summary: New Fantastic Comsigan Loader - Korean School Timetable Scraper
Author: YourName
Requires-Python: >=3.6
Requires-Dist: selenium
Requires-Dist: webdriver-manager
Dynamic: author
Dynamic: requires-dist
Dynamic: requires-python
Dynamic: summary
